mlr_cpp.cpython-310-darwin.so
MLR/mlr_wrapper.py
MLR/__init__.py
MLR/core/__init__.py
MLR/tests/test_model.py
MLR/tests/__init__.py
MLR/tests/test_summary.py
mlr_cpp-1.1.0.dist-info/RECORD
mlr_cpp-1.1.0.dist-info/WHEEL
mlr_cpp-1.1.0.dist-info/top_level.txt
mlr_cpp-1.1.0.dist-info/METADATA
